<?xml version="1.0" encoding="UTF-8"?>
<!--This file was created by G+Smo 21.12.0-->
<xml>
 <Geometry type="TensorBSpline2" id="0">
  <Basis type="TensorBSplineBasis2">
   <Basis type="BSplineBasis" index="0">
    <KnotVector degree="2">0 0 0 0.043478 0.08695700000000001 0.130435 0.173913 0.217391 0.26087 0.304348 0.347826 0.391304 0.434783 0.478261 0.521739 0.565217 0.608696 0.652174 0.695652 0.73913 0.782609 0.826087 0.869565 0.913043 0.956522 1 1 1 </KnotVector>
   </Basis>
   <Basis type="BSplineBasis" index="1">
    <KnotVector degree="2">0 0 0 0.043478 0.08695700000000001 0.130435 0.173913 0.217391 0.26087 0.304348 0.347826 0.391304 0.434783 0.478261 0.521739 0.565217 0.608696 0.652174 0.695652 0.73913 0.782609 0.826087 0.869565 0.913043 0.956522 1 1 1 </KnotVector>
   </Basis>
  </Basis>
  <coefs geoDim="2">0.9420499999999998 0.5945200000000002
0.886906 0.6041560000000001
0.7539849999999999 0.6355010000000001
0.6600939999999997 0.5604819999999999
0.5489359999999999 0.5186389999999996
0.4205909999999999 0.5176889999999998
0.299647 0.524764
0.175916 0.535093
0.05434600000000001 0.508453
-0.07045199999999996 0.5131839999999999
-0.189018 0.547906
-0.311205 0.5683120000000002
-0.430563 0.5996459999999999
-0.5482940000000001 0.6346159999999998
-0.6706029999999999 0.602106
-0.795363 0.587086
-0.877336 0.487006
-0.87759 0.361436
-0.877987 0.237603
-0.900844 0.116685
-0.929329 -0.004226999999999981
-0.98369 -0.116666
-0.993097 -0.239468
-0.99642 -0.363541
-1 -0.42517
0.9723570000000001 0.57385
0.9113631293272428 0.5692104655601318
0.7782915754108299 0.6082743254281129
0.6926041952791435 0.5589892834381229
0.5624196022131296 0.5056576010793403
0.4277619001938582 0.5030073551462657
0.3064081683103463 0.5087398165892651
0.1857842076523692 0.5179417219033375
0.06947301936681982 0.4974328613561625
-0.06222232405785932 0.4970942020746314
-0.1873616067151083 0.5288178837976012
-0.3076532934139015 0.5488259056903639
-0.4373877849123805 0.5782861246723043
-0.5490403990906356 0.604423846602925
-0.6634407110623226 0.5791618505653555
-0.7795800040111458 0.5540994500471326
-0.8423516530605435 0.4813114422709808
-0.8523080403681981 0.3701903398365174
-0.8567202388293647 0.2387402591573881
-0.8800883857610213 0.1116311082856773
-0.9166188597590655 -0.02272219261669028
-0.9631609101955211 -0.1350528199770853
-0.9707211364485915 -0.2724550023662354
-0.9753340357042174 -0.4076818189419472
-0.965038 -0.446523
1.008717 0.5040960000000001
0.9467932872189144 0.5201578534814386
0.8183886804397156 0.5462471962103919
0.7198306118585283 0.5273360540843433
0.5858590094291789 0.4833176017201368
0.445250930191524 0.4729955093585885
0.3218355270581659 0.4774907166827151
0.2056083788511223 0.4836365008658865
0.09303011552447304 0.4720022555732681
-0.03745265151041055 0.4673465674268913
-0.1685039387524961 0.4889530755069895
-0.2916951436757487 0.5092398384762891
-0.4174299122879777 0.5290990145995214
-0.5303343156335152 0.5449923395754037
-0.6301563376414192 0.5296973488869883
-0.7223641758064675 0.4982359236229421
-0.7767410242510646 0.4387610578530818
-0.8007430633417063 0.3450791497120446
-0.8160956324678972 0.2251583923471833
-0.8447394517094883 0.09360520802079964
-0.885028248478376 -0.04559644604444779
-0.9225065750629162 -0.1701516852068888
-0.9303955074294097 -0.3104252275958889
-0.8930842360457077 -0.4164462875728213
-0.871874 -0.457395
0.950099 0.4459109999999999
0.9280660384601944 0.4701958821297625
0.8337886508653811 0.4914006740307817
0.7274485757357521 0.4861864692145512
0.5987554271985887 0.4571206615599339
0.4594994905605398 0.444366268111944
0.3371261276838553 0.4460741353516322
0.2246685040070242 0.4501648674864458
0.1145229362842874 0.4440111174213499
-0.008741077861439073 0.4384408904383119
-0.1386524973369909 0.4506922220392804
-0.2625595436222846 0.4675591341069028
-0.3828607811230522 0.4808849756268787
-0.4923552789316286 0.4884111832190359
-0.5856433729352498 0.4762581447963246
-0.6642495592795939 0.4446935313866391
-0.7183750270133822 0.389670970564971
-0.7513501493281858 0.3079601100247733
-0.7769353456691236 0.2004505530998315
-0.8101655474483447 0.0744868968268656
-0.8506869649827229 -0.06025461346814365
-0.885616046810203 -0.2053520490659492
-0.8801992143364622 -0.3267543747438241
-0.826780441968726 -0.5165067721180712
-0.878766 -0.555457
0.939838 0.3737809999999999
0.9038275275785932 0.4024926001412272
0.8338131687460648 0.4374505371326203
0.7278611920195226 0.4452592533844857
0.6001908373172071 0.4272087070745427
0.4678660531734216 0.4155291683806863
0.3504198494231536 0.4147436097493249
0.2422101755602331 0.4171165480632091
0.1361165732185063 0.4141548095406395
0.02139116587509848 0.4093850487661419
-0.1020776041058614 0.4147006204443962
-0.2236947883190048 0.4261347149884052
-0.3389865827361564 0.4345845204820085
-0.4444278018296786 0.4361783500445493
-0.5342948015548552 0.4236495751276221
-0.6082571880788737 0.3933473961825462
-0.6638385327343088 0.3428877955020139
-0.704001932393894 0.2699016150753065
-0.7376908432997997 0.1741158817060785
-0.7742067999589531 0.05787772621706011
-0.8155977420151902 -0.07311365541435366
-0.8492275878611988 -0.2210343226273867
-0.8279411608128754 -0.3737237185733199
-0.7983443849511991 -0.57858346847416
-0.8208490000000001 -0.634061
0.984359 0.311895
0.9288041746492135 0.3250987689410431
0.8298584161420459 0.3878562524590352
0.721202575424668 0.4063738761059426
0.5925415037554034 0.3953803707370089
0.4700900272496842 0.3854301288004445
0.3603021080977127 0.3832060380353726
0.258128050484834 0.3841413256799766
0.1576962293356541 0.3828471002707872
0.05174216358176742 0.3794824692410892
-0.0625012474801413 0.3806263240642249
-0.1784627369835924 0.3865061109670422
-0.2892402994667491 0.3908302045294041
-0.3908044897897033 0.3885538972987082
-0.4790070743200968 0.3749778117119404
-0.5522939064093246 0.3463786144866906
-0.6106903156848057 0.3004095509556238
-0.6568029141889924 0.2353731402611946
-0.6964567181226644 0.1501648226399787
-0.7359573407034951 0.04536568249009032
-0.7786217785127507 -0.07976299116972296
-0.8120586667199486 -0.2213743549112784
-0.7913762903985445 -0.4064825456645899
-0.7518244749995444 -0.5659098713492521
-0.736375 -0.614314
1.00853 0.238683
0.9562845224323353 0.2618205175479382
0.8225177445170821 0.3468728155640601
0.7037871922466912 0.3708265172210703
0.5771745961981487 0.3621074882613531
0.4671058101248606 0.3537606576545715
0.3664581066144101 0.3509480029212132
0.2721042269378104 0.3508702782961679
0.1786994060629161 0.3503569672042476
0.08157175241740156 0.3483353355388176
-0.02241177949267403 0.3475506445883587
-0.1303121446208666 0.349165356772701
-0.2357609225455474 0.3498473122933042
-0.3337813128117233 0.3450835176731131
-0.4207765133484195 0.3309489228825323
-0.4949649852306617 0.3043180745351783
-0.5564814870939979 0.262959067171146
-0.6075344452515989 0.205385005651165
-0.6519047242068652 0.1303953880910472
-0.6946854062242791 0.03638949145808523
-0.7365839804897371 -0.07479877478876573
-0.7779322924547414 -0.215550633015566
-0.7599127598721904 -0.4031139164780663
-0.6990856383061568 -0.5281842687960705
-0.682734 -0.5566179999999999
0.9705379999999999 0.1765760000000001
0.9349156090337671 0.2272773781645617
0.8004815204085036 0.3200392004943813
0.6700230230316628 0.3367743804068604
0.5574094553814686 0.3270669373341296
0.4596364172663214 0.3205066504522743
0.3695697414217181 0.3174751303153777
0.2838761699939223 0.3169381582698392
0.1985295735853991 0.3167759705701707
0.1103244602244324 0.3157897787856913
0.01664055204457915 0.3145240637033369
-0.08180835086661886 0.3136082383539666
-0.1805692763857402 0.3115110613827639
-0.2745542700604037 0.305069899677251
-0.3600916744228396 0.2910090534817611
-0.4351524647104007 0.2666293296346
-0.4995473423370014 0.2299518385602501
-0.5545790355053521 0.1794808447756902
-0.6031174577851923 0.114368051349689
-0.6486302006515418 0.03203886478519435
-0.6902483122295691 -0.06587792512273871
-0.7385813903554667 -0.1886581544928421
-0.7411984862295824 -0.3697412515902821
-0.6380378096732842 -0.5292606941859828
-0.574117 -0.59115
0.8872390000000001 0.187111
0.8683933928249945 0.2365510473070529
0.7480202864096561 0.3010401111454097
0.6278085623020282 0.2991096448810597
0.5353963645522339 0.2906756259045936
0.4493739823235217 0.2852832286980946
0.3703762279411158 0.2825261530392744
0.2934820435865069 0.2819683939273886
0.2167216803220662 0.282049454082631
0.1374754867177115 0.2818081184442756
0.05379492358644167 0.2808064154128226
-0.0347045356330602 0.2788992624219919
-0.1254937175188515 0.2751983791224477
-0.2143324853943422 0.2677648518056508
-0.2974502751476168 0.2541944627897245
-0.3725582390729403 0.2322513347889557
-0.4388936223728495 0.2002004666890892
-0.4971518992413306 0.1566733282072315
-0.5488574894891936 0.1006460986535179
-0.5970887805913315 0.03118828056616407
-0.6402582587667814 -0.05639247555127958
-0.6854663444773595 -0.1507298497777258
-0.724695868289394 -0.3031250423842316
-0.6469780388756994 -0.472046714190849
-0.591717 -0.479422
0.8245909999999999 0.208792
0.7831835406790493 0.2543083202970342
0.6816560713044688 0.2694058302824354
0.5898509916082404 0.2582316771273152
0.5118865926406815 0.2525073020857942
0.4386253153632309 0.2478386454416125
0.3693049532291222 0.2459328552023879
0.301248323974076 0.2456141972966367
0.2329572159295286 0.2460224413807667
0.1625865649097016 0.2463494470314574
0.08851726217783451 0.245915378952731
0.009951607641051297 0.2440787542182837
-0.07203625579754425 0.2399729922736933
-0.1544412718004559 0.2323217628514659
-0.233797118170476 0.2195453371370585
-0.3075625085688061 0.2000264164677499
-0.3745261797240583 0.1723531957064135
-0.4347273036354088 0.135439777526171
-0.4889784110598751 0.08807028881514745
-0.539038279581328 0.03006259863745986
-0.5858373783585542 -0.04330808327780578
-0.624002605954164 -0.1249758150956314
-0.6807162731128784 -0.2292121012668656
-0.682398922572883 -0.351889962970958
-0.62538 -0.414045
0.7457289999999999 0.227935
0.7115754955279419 0.2345270745708883
0.6253691537553341 0.2232099949685226
0.5565859917169129 0.2167070006674908
0.4900350501350172 0.2113756910171268
0.4278846138119496 0.2084072126650187
0.367151473827896 0.2074108161825982
0.3073507915451374 0.2076428375756489
0.2471554296170235 0.2084764103722376
0.1853076480707554 0.209322248701431
0.1204220531291771 0.2095467711833824
0.0515204896543533 0.2083690183726223
-0.02126440638675187 0.2048216326094365
-0.09617466186222612 0.1977976163601115
-0.1703777686482704 0.1861908815423748
-0.2412719377239914 0.1689749061691184
-0.3072252907606514 0.145212053466277
-0.3678554417638978 0.1141674478659197
-0.4233061665101657 0.07502305843093582
-0.4750805553414925 0.02692186386096562
-0.5230131915658633 -0.03105669160207403
-0.5675548588590005 -0.105739476450956
-0.6000959345199537 -0.1777436052814512
-0.6570045609064751 -0.26777369344444
-0.653417 -0.308441
0.687066 0.1899009999999999
0.6474704798164432 0.1842581418361524
0.5853614541953425 0.177753461910194
0.5264813569360609 0.1713815023488876
0.4712903366145877 0.1680279833193917
0.4172959143697466 0.1667248465345197
0.3643684401845269 0.1668746299499936
0.3119393108059383 0.1678276638542493
0.2593008523973235 0.1692016568095533
0.205435086888448 0.1705778112652524
0.1492039412066966 0.1714770558391744
0.08956597626793661 0.1712103731917674
0.02606623306654399 0.1688238741560252
-0.04058976703230699 0.163197109469412
-0.108450111936629 0.1533030114839543
-0.1750767862900404 0.1383969783490711
-0.2385543484545724 0.117991252757405
-0.2978703290702609 0.09176231152198766
-0.3531386684523055 0.05950103872249601
-0.4046236727480537 0.02071283131563761
-0.4544093031044181 -0.02542482271389968
-0.5010994633733661 -0.08185407914512199
-0.5428759697245427 -0.1582958651159971
-0.564975304592036 -0.2250252060361628
-0.600504 -0.256198
0.6299969999999999 0.1404110000000001
0.6014341259555409 0.1358358892543657
0.5503164445432001 0.1270346633858915
0.5021076455245244 0.1232015032240008
0.4542937909813316 0.1222728290622128
0.4071959831361185 0.1228401751255511
0.3608627618332454 0.1242100573310991
0.3150993094292676 0.1260145322871008
0.2693568065116456 0.1280001117627573
0.2228555525725 0.1299401095268957
0.1746448944453187 0.1315097308098804
0.1237420066980037 0.132204345796009
0.06938034634935475 0.1312354570681106
0.01145551800019495 0.1275350035874838
-0.04905443173763324 0.1199769658438011
-0.1102417194077786 0.1077249754565811
-0.1700271569591895 0.09040565199428652
-0.2269491627260533 0.06800698400837257
-0.2803105369113982 0.0407548291774954
-0.3305764434279165 0.009015679357666451
-0.3781183498600204 -0.02711890979612108
-0.4266436676776659 -0.06825329392166934
-0.4732483565753808 -0.1197396616125318
-0.5157517598290067 -0.2040713638668125
-0.510613 -0.246057
0.5856940000000002 0.08208400000000005
0.5652102704074298 0.0756872779409471
0.5235819591536763 0.07207299444799076
0.4807990994936258 0.07257001103381611
0.4384089430717992 0.07439326311779593
0.3968970422059011 0.07680950068262204
0.3563886524659334 0.0794179083659341
0.3166511061171773 0.08208018866714495
0.2772211806795519 0.08471518113559551
0.2374561543117668 0.08722827232662433
0.1965908453000311 0.08944811774823735
0.1537741417263534 0.0910544010446066
0.1081666665151308 0.0914958813879706
0.0591793464293402 0.08991052012959277
0.006877005840409955 0.08517267092780145
-0.04770037519510884 0.07618853084121258
-0.1027509800992489 0.06228484194481376
-0.1564300967487728 0.04337971293406484
-0.207510722218177 0.01982960525693045
-0.2553354387703118 -0.007687695170419007
-0.3005596797218962 -0.03813579360901931
-0.3431240487033153 -0.07035175150923245
-0.3912472021826948 -0.1026180490211539
-0.43943388699315 -0.141167534886312
-0.454581 -0.1676550000000001
0.5610490000000001 0.01127299999999987
0.5402285299682295 0.01204224793386832
0.4991254520550554 0.01623093121227281
0.4597014833051731 0.02057778716286351
0.4218051044683864 0.02486593459747199
0.3853971546388362 0.02885812454687187
0.3503016708092486 0.03254292447073093
0.3161949229296126 0.03597570502130376
0.2826239912524338 0.03921476793263579
0.2490534269412734 0.04227526942707294
0.2148791086932418 0.04509680583571296
0.1794286451104152 0.04751657253547958
0.1419659646471974 0.04920533504475322
0.1017566131525784 0.04959028740946447
0.05827483152934931 0.04777449623553542
0.01157458040098791 0.04259378123937396
-0.0373887734811863 0.03292491155622546
-0.08690929407855885 0.01813439787223159
-0.1352269916266794 -0.001700763410208195
-0.1811914121185002 -0.02601224845982442
-0.2242027305852849 -0.05390317035157532
-0.2643445638779605 -0.08419899358452021
-0.3004335712362839 -0.1142667092863806
-0.3401704072410725 -0.139042444993264
-0.364706 -0.150303
0.5256400000000001 -0.05174400000000001
0.5062557629957387 -0.04655499574766253
0.4697922925873579 -0.0387346711249541
0.4352563862520844 -0.03177744490476042
0.4024902927489222 -0.02582054660332145
0.371398020522369 -0.02073851774912461
0.3417223474250901 -0.01631025995747359
0.3130965755418047 -0.01231795970268079
0.2851014903443212 -0.008603490222491517
0.2573016167037316 -0.005083571420801625
0.2292460593922441 -0.001740307084344472
0.2004465151975297 0.001363254211300013
0.170356439841536 0.004069609898632254
0.1383516289254638 0.00606575521100694
0.1037614218365748 0.006804910050676849
0.06602054315111316 0.005401220485028002
0.02499559848306787 0.0006488837916017731
-0.01862829808265409 -0.008715787872440983
-0.06325506987653706 -0.02350745071943128
-0.106957685409922 -0.04369131728507647
-0.1485268337953398 -0.06853750612267573
-0.1877302426922101 -0.09722318042604527
-0.2253358788681455 -0.1295710465720039
-0.2584431166220298 -0.1639689974045576
-0.278708 -0.176216
0.4776629999999999 -0.109721
0.4633450240487311 -0.1037515560375849
0.4341778990981828 -0.092620467100193
0.4057754577298509 -0.08393289856501385
0.3789530325692549 -0.0771943447501966
0.3536963860872957 -0.0717421573892294
0.3296997747143851 -0.06706828490594796
0.3065912597166844 -0.06284455263238653
0.284024269274362 -0.05887276838953759
0.2616784200609457 -0.05504332883871899
0.2392505753661638 -0.05130955019463024
0.2164305091526748 -0.04766952779408373
0.1928730610740412 -0.04418563346293658
0.168167474227833 -0.04099100692324098
0.1418140333030562 -0.03834833727035525
0.113204042078439 -0.0367153265318112
0.08169725384674553 -0.03689197429568214
0.04683422319407926 -0.04008137749048457
0.008725289167768269 -0.04775700080461587
-0.03149519433330383 -0.06121788530044492
-0.07157502373944069 -0.0809028568626079
-0.1091300550276446 -0.105914885678868
-0.1438491712158488 -0.134615988103797
-0.1788080138324719 -0.1684740542581261
-0.1926019999999999 -0.191833
0.4275640000000001 -0.161079
0.4150023655029269 -0.1521563028142153
0.3914289706088123 -0.1415759562062828
0.3700362379387101 -0.1343851763305105
0.3502456427301583 -0.1288745401316701
0.331558316371432 -0.1242046208125247
0.3135899127022386 -0.1199555481674573
0.296067094817581 -0.1159077819077198
0.2787846953669642 -0.1119428989680874
0.2615777310442899 -0.1079908321575972
0.2442961251595563 -0.1040115202658837
0.2267897786623141 -0.1000021339971134
0.2088890905102179 -0.09596341741512315
0.1903915455092329 -0.09193980679554636
0.1710313870666189 -0.08801283562254048
0.1504695758673922 -0.08436578973673792
0.1282335106849795 -0.08130707774997115
0.1037227219424166 -0.07943946832658522
0.07628601489176168 -0.07982384941360832
0.04534202484568439 -0.08398681622605775
0.01067368761119369 -0.09377103710335311
-0.02666457851109361 -0.1109250442297867
-0.06230617375210301 -0.1355570401060934
-0.09112288509858768 -0.1629718602987618
-0.101505 -0.173643
0.356652 -0.194433
0.3516060109826478 -0.1933616499924978
0.340920018842634 -0.1905882945867561
0.3297630276557786 -0.1873653032133685
0.3182051895440379 -0.1838878350419501
0.3063263626195782 -0.1802638990011257
0.2941929223889621 -0.176546884533332
0.2818564420711731 -0.1727490622688178
0.2693488202605905 -0.1688620888780514
0.2566827722593594 -0.1648720638178325
0.2438546034280238 -0.1607666693034691
0.2308422475012399 -0.1565148347770475
0.2176093711862328 -0.1521219905795365
0.2040943966870734 -0.147576115824837
0.1902142249153438 -0.1428854080464046
0.1758301583957615 -0.1380357893401988
0.1607729738766579 -0.1331040554336316
0.1447853034422082 -0.1282146064624736
0.1274854634987221 -0.1236444625828236
0.1084450312342939 -0.1201160213349143
0.08725681233772331 -0.1189276058793517
0.06325811897554012 -0.1218800942032959
0.03461923396628075 -0.1315938208695963
-0.0002111758840073197 -0.1528824837048152
-0.01876500000000003 -0.172151
0.324022 -0.259765
0.3199821016496209 -0.257908812443965
0.3116704760048004 -0.2542822195231287
0.3031090652881929 -0.2507195090213054
0.2943228553208814 -0.2471478940590625
0.2853350604191209 -0.2435117292648563
0.2761675975857105 -0.2397738248501673
0.2668390533611782 -0.2359159744216359
0.2573673335295659 -0.2319269133661615
0.2477678551567044 -0.227801255787644
0.2380557706009707 -0.2235159526466896
0.2282429400471162 -0.2190977655580573
0.2183368427802341 -0.2144954036326067
0.2083420012508315 -0.2096971917252399
0.1982481224789576 -0.2046704499425744
0.1880547592843582 -0.1994248067749206
0.177709189652786 -0.1938513939675339
0.1671422022941076 -0.1878627778543418
0.1562629746005533 -0.1813915744722978
0.1448664094629917 -0.1742602318196377
0.1326482131204523 -0.1664407258517327
0.1192753289558832 -0.1582287408090093
0.1047265941350743 -0.1506780470049763
0.09009997964803573 -0.1459093850894363
0.08338500000000004 -0.145525
0.3065519999999999 -0.332171
0.3024035434372538 -0.3301937217038734
0.2941193681551375 -0.326254160042276
0.2858403885253511 -0.3223516458667273
0.2775552963713996 -0.3184671218097532
0.2692560120767333 -0.314586996241494
0.2609398429317875 -0.3106925619950269
0.2526100797377733 -0.3067563806232168
0.2442715490786842 -0.3027584364744665
0.2359327243039231 -0.2986736927550178
0.2276022278906427 -0.2945000389368255
0.2192944264114833 -0.2901382951615598
0.211019599390442 -0.2856416715979513
0.202787384726522 -0.2809744208905464
0.1946176345438779 -0.2761167942236323
0.1865040113840084 -0.2710194751279998
0.1784940719457866 -0.2657141825118183
0.1706101410841634 -0.2601959904913326
0.1628531306459928 -0.2543857658676777
0.1552643315687365 -0.2482548626445059
0.1478785508118885 -0.2416762384455766
0.1407105651193197 -0.2345250550801175
0.1336939760223488 -0.2268533625858372
0.1266635521977129 -0.2191337892474541
0.123113 -0.215364
0.2879260000000001 -0.403172
0.284340175577982 -0.4018735922848202
0.2769371608542557 -0.3992340032014119
0.2693442596083278 -0.3963781912354311
0.2615924978724105 -0.3933304978183282
0.2537141422653748 -0.3901055574387017
0.2457359151123295 -0.3867296372817428
0.2376819105327646 -0.3832258980271831
0.2295743150415868 -0.3796072845187124
0.2214325402030395 -0.3758871514849636
0.2132787157974732 -0.372034523317498
0.2051207867872196 -0.3682288814004483
0.1969852702087638 -0.364308499076967
0.1888999294112552 -0.3602922802800987
0.1808694904374286 -0.356198284626722
0.1729666907138732 -0.351960167084196
0.165118260182112 -0.3476676453859142
0.1573381146601394 -0.3433196052811655
0.1497002963864278 -0.3388550973284465
0.1421823807137328 -0.3343299129201228
0.1347913369161071 -0.3297645493079535
0.1275295676333079 -0.3251690437880745
0.1204599169274225 -0.3203395738741414
0.1136983769080953 -0.3148230462966471
0.1104670000000001 -0.311695
0.2902130000000001 -0.47678
0.2853528160717003 -0.4770596142116247
0.2755796502855699 -0.4756021627473968
0.2658810748839593 -0.4733443246643459
0.2562907854759366 -0.470668002612658
0.2468083528514384 -0.4677833741704738
0.2374258997901286 -0.4647755854076894
0.2281328648926253 -0.461674559985196
0.2189185171083905 -0.4584949573378598
0.2097735075262614 -0.4552331157285467
0.2006816053985401 -0.4519638615255211
0.1916617080797693 -0.4482460107301588
0.1826830889915676 -0.444512160526788
0.1737126989761115 -0.44072200193253
0.1647768504813472 -0.4368329616680859
0.1557259709498611 -0.433107396446562
0.1468191917194512 -0.4291487461447527
0.1380615121235313 -0.4249575542614507
0.1292738509088101 -0.4208893498545208
0.120579385527845 -0.4167211166693139
0.112009928058195 -0.412448158607643
0.1037018560291396 -0.4078135547762007
0.09579715494800434 -0.4025935794533035
0.08852764201360475 -0.3963808055818544
0.08541899999999969 -0.392311
0.2954870000000001 -0.5530040000000001
0.2875092285659295 -0.5478585766269316
0.2737593496529382 -0.5436118760943398
0.2612760074564859 -0.5414801658701207
0.2496075797465975 -0.5403041190999858
0.2385000386221501 -0.5394483628079602
0.2277939606653883 -0.5386151810854209
0.2173901385895864 -0.5376435457336012
0.2072253625550544 -0.5364158594858955
0.1972594152144398 -0.5348581405255547
0.1874868915825101 -0.5327044987171836
0.1778186361653773 -0.5310726987286962
0.1683123829831679 -0.5287206692956592
0.1590243100437698 -0.5257231977560136
0.1498482103671603 -0.5221984822386652
0.1411224885008264 -0.5175018205487341
0.1320985313980156 -0.5127524697398216
0.122790303264551 -0.5078297799812183
0.1136150066696429 -0.5020038584164547
0.1042307848138944 -0.4958638959807878
0.09455751915645361 -0.4894342226197349
0.08427039624787991 -0.4833524724988947
0.07299963283867128 -0.478421481346519
0.06007364479101907 -0.476257699578726
0.05220599999999997 -0.477971
0.2708699999999999 -0.58068
0.2659419999999999 -0.580768
0.2560899999999997 -0.580944
0.246237 -0.58113
0.2363839999999999 -0.581313
0.2265299999999999 -0.5814859999999999
0.2166769999999998 -0.581669
0.2068240000000001 -0.5818489999999999
0.1969689999999999 -0.582043
0.18712 -0.5821730000000001
0.1772529999999999 -0.582548
0.1675899999999999 -0.580426
0.1579660000000001 -0.578424
0.1482479999999999 -0.576562
0.1387499999999999 -0.5742350000000001
0.1287290000000001 -0.573062
0.120269 -0.568422
0.1127609999999999 -0.561815
0.1049259999999999 -0.555926
0.09722999999999993 -0.549731
0.0894680000000001 -0.543675
0.08173999999999992 -0.537555
0.07399199999999984 -0.531464
0.06627099999999997 -0.525346
0.06238600000000005 -0.5223100000000001
</coefs>
 </Geometry>
 <MultiPatch parDim="2" id="1">
  <patches type="id_range">0 0</patches>
  <boundary>0 1
0 2
0 3
0 4
</boundary>
 </MultiPatch>
</xml>
