<?xml version="1.0" encoding="UTF-8"?>
<!--This file was created by G+Smo 21.12.0-->
<xml>
 <Geometry type="TensorBSpline2" id="0">
  <Basis type="TensorBSplineBasis2">
   <Basis type="BSplineBasis" index="0">
    <KnotVector degree="2">0 0 0 0.043478 0.08695700000000001 0.130435 0.173913 0.217391 0.26087 0.304348 0.347826 0.391304 0.434783 0.478261 0.521739 0.565217 0.608696 0.652174 0.695652 0.73913 0.782609 0.826087 0.869565 0.913043 0.956522 1 1 1 </KnotVector>
   </Basis>
   <Basis type="BSplineBasis" index="1">
    <KnotVector degree="2">0 0 0 0.043478 0.08695700000000001 0.130435 0.173913 0.217391 0.26087 0.304348 0.347826 0.391304 0.434783 0.478261 0.521739 0.565217 0.608696 0.652174 0.695652 0.73913 0.782609 0.826087 0.869565 0.913043 0.956522 1 1 1 </KnotVector>
   </Basis>
  </Basis>
  <coefs geoDim="2">0.9998600000000002 0.28578
0.9706129999999999 0.316477
0.8776520000000001 0.311101
0.7930789999999999 0.3182989999999999
0.702315 0.310322
0.6216880000000002 0.335634
0.5389299999999999 0.359244
0.4501740000000001 0.363735
0.3635940000000002 0.369482
0.2756830000000001 0.365834
0.188329 0.3658920000000001
0.1007370000000001 0.364369
0.01324700000000001 0.363525
-0.07428699999999999 0.3623910000000001
-0.161801 0.361378
-0.249327 0.3603209999999999
-0.33684 0.3592629999999999
-0.424377 0.3582520000000001
-0.511862 0.3571130000000001
-0.599464 0.356278
-0.686796 0.354736
-0.774756 0.35484
-0.861237 0.351062
-0.9516250000000001 0.357645
-0.98563 0.32916
0.99583 0.2682339999999999
0.9653847898554229 0.2917999982429531
0.8721948995115776 0.304843481051757
0.7770102225352253 0.3077721604324598
0.6897280788585962 0.3074317316739092
0.6007738211633868 0.3335632212685918
0.520406092452377 0.3486183572311688
0.4332750759722379 0.351561061042661
0.3502260041433214 0.3548892353530439
0.2639096522092546 0.3516439400938305
0.1782066094250505 0.3512971028896512
0.09204751016703661 0.3497190671865746
0.005750357335901235 0.3487546628198954
-0.0807234095475583 0.3475876793883142
-0.1673456194418911 0.3465451286012224
-0.2540528854139822 0.3454729874787794
-0.3409004237490019 0.3444356400499397
-0.4277197852802005 0.3433817474777043
-0.5148659524055644 0.3423534036783609
-0.6015279595205751 0.3412762936019952
-0.6895895414659828 0.3402039563790943
-0.7748969653444895 0.3390642228968013
-0.8667578641076708 0.3373470097975653
-0.943517057439449 0.3356136844354224
-0.987666 0.315196
0.9917019999999999 0.223649
0.9503473657860473 0.2675805749598634
0.8432117472691691 0.2895880563878785
0.7446446571374894 0.2943386589110626
0.6531091173565606 0.3024707561652093
0.5668978568020504 0.3198226445997248
0.4865636910184916 0.3238587493113672
0.4059926678532146 0.3253180811424051
0.3252590066067746 0.32538040429763
0.2427150328054002 0.322780791163885
0.1595699303269387 0.3217149760104794
0.07588261523388473 0.3201137485743615
-0.00834901500478713 0.3189708454405323
-0.09296747642315317 0.3177770136164372
-0.177944502463149 0.3167003627136024
-0.2632024544845978 0.3156423788756185
-0.3486822333328008 0.3146110164438161
-0.4344051666952762 0.31360316815075
-0.5202653460408451 0.3125619229156379
-0.6064497925508154 0.3115375190381864
-0.6927094735630264 0.3103443386657331
-0.7792623837746891 0.3089275277573958
-0.8660630165998312 0.3069301869983751
-0.94708307969898 0.2991407360450944
-0.991849 0.287271
0.9502429999999999 0.223757
0.9140338162862593 0.2545921395636542
0.8087796606769582 0.2767324444182291
0.7079059748710985 0.2856050393515298
0.6166530439488385 0.2931661037929774
0.5365952470767663 0.2988553738914204
0.4589794321003551 0.2977293846138753
0.3816465918783987 0.2975633335898838
0.3032871178502636 0.2957459055058519
0.2234377735481858 0.2934003704659173
0.1425382966421154 0.2918467396388235
0.06087048175184129 0.2902334479204623
-0.02155512646208679 0.2889788786308859
-0.1045466697976285 0.2877796452019939
-0.1880500423534129 0.2867018619007597
-0.271951751733049 0.2856650951732002
-0.3562132315994284 0.2846728457490471
-0.4407634636308161 0.2836910368085526
-0.525632969039959 0.2827044514331175
-0.6107565597194295 0.2816606271753921
-0.696194737773379 0.2804500746355814
-0.7817899945444836 0.2787933738629909
-0.8669657164978138 0.2759697474975033
-0.9501193929724066 0.2671428348221465
-0.995848 0.259341
0.9113580000000001 0.221994
0.8740188079123425 0.2455961157646184
0.7686329755415937 0.2681755641095436
0.6703626699305945 0.276954642581737
0.585988261513597 0.2768348480424219
0.5097563193421728 0.2736648979550513
0.4354744163654409 0.2708124795131189
0.360077782419354 0.268639870875745
0.283871465471957 0.2659738438024388
0.2059749230544958 0.2635796877601864
0.1269734691626958 0.2617433945878396
0.04697562508630737 0.2601157570651169
-0.03389007003874378 0.2588033457844969
-0.1154591293431725 0.2576187813189351
-0.1976348829655986 0.2565577877080784
-0.2803089387426048 0.2555613859755612
-0.363407140148624 0.2546106266706478
-0.4468868672759966 0.2536806318146086
-0.5307062661810069 0.2527337545563836
-0.6148757418598984 0.2517154142450093
-0.6992934397263761 0.2504607211056412
-0.7839797586220032 0.2486516104203475
-0.8681739533713508 0.2452458025032971
-0.9531204563878815 0.236993815429842
-1.00037 0.2314330000000001
0.871831 0.220544
0.8329748077228372 0.2397336982980851
0.725435222177097 0.2620600621230838
0.6386578154394105 0.2643528926659252
0.5590776470332102 0.2538215002261376
0.4875306277950699 0.2470632463954226
0.414699779749214 0.2427124018038375
0.3412461164834553 0.2390727452976074
0.2665419572564729 0.2359693431377316
0.1902341872184292 0.2334211930399059
0.1127423118831956 0.2314321840869598
0.03414122404582853 0.2297951760147528
-0.04539031148806094 0.2284661108476375
-0.1257117993122863 0.2273097939516648
-0.2067043634482235 0.2262838252540417
-0.2882516280702589 0.2253347467270064
-0.370277271876295 0.224438245450324
-0.4527193194440479 0.2235631919239485
-0.5355459441802798 0.22266951970106
-0.6187176565853941 0.2216805788460423
-0.7021785716849398 0.220413724514663
-0.7858938417457271 0.2185203961068742
-0.869463766628741 0.2148725340733821
-0.9550447444867488 0.2079408627065872
-0.999539 0.203169
0.832303 0.2192129999999999
0.7867536148928178 0.2369148642555184
0.6881025127950171 0.2548605175110516
0.6112728469414832 0.2449627704879827
0.5372971031808229 0.2269831912305929
0.4682781683060828 0.2196168920415623
0.3965561219206279 0.2135407864334043
0.3247287433093442 0.2091099079153647
0.2510429679335255 0.205698322681896
0.1760427468869643 0.2029959190071263
0.09973261941506717 0.2009392937105733
0.02230200593160769 0.199300089740143
-0.05609935969904456 0.1979854762035616
-0.135330860128854 0.1968685722088165
-0.2152640824303551 0.1958892861535597
-0.2957867626896631 0.1949951289789717
-0.3768115617702295 0.1941586915113985
-0.4582753829554408 0.1933453276613041
-0.5401342822376036 0.1925108404720293
-0.6223388394199769 0.1915634667607375
-0.7048652133834414 0.190327014750592
-0.787615737447356 0.1883960014552951
-0.8707741401673453 0.1849249776230981
-0.9554292507960838 0.17893641362618
-0.999259 0.1749559999999999
0.7933839999999999 0.2172790000000001
0.7385860786944718 0.2362675667887941
0.6605275871087721 0.2432040417552514
0.5873251558604442 0.2178483436335888
0.5205209871313374 0.1991852074731826
0.4508438618901527 0.1911051545739275
0.3811821861664586 0.1835690137365337
0.3099872779881316 0.1788851222073579
0.2372508412746279 0.1751402403587226
0.1632046218057752 0.1723713713758523
0.08784207578303094 0.1702782315125844
0.01138385963999822 0.1686581572074095
-0.06606429254214852 0.1673775490443747
-0.1443436186622924 0.1663093552186217
-0.2233351571269172 0.1653845301276246
-0.3029231475910448 0.1645504626515857
-0.3830197621589175 0.1637777503177594
-0.463559257128098 0.1630317862288086
-0.5444898492901924 0.1622610740791939
-0.625771073625969 0.1613760318572867
-0.7073660903572256 0.1601926370115291
-0.7892907593044913 0.1583445807211716
-0.8717643767978441 0.1551704482747684
-0.955704800647783 0.1500789594204868
-0.998783 0.146725
0.752791 0.216887
0.6942157560048847 0.2336021642640609
0.6406699322797442 0.2253121174364404
0.5696829335426303 0.1847696278745999
0.5051229018625369 0.1720211686726986
0.4362063262342213 0.1608511116420073
0.3678254212736953 0.1534089174872668
0.2968510961757171 0.1482779443631898
0.2249699169220791 0.1443717638150134
0.1515457890619345 0.141571262615726
0.07698010129085242 0.1394685165413047
0.001299473822686137 0.1378909628740783
-0.07533312349491061 0.1366563764775041
-0.1527894912108886 0.1356453804385083
-0.2309406995160695 0.1347785444974803
-0.3096783849580087 0.134007650642319
-0.3889155388961338 0.1333021327090895
-0.4685860702445649 0.1326253889208212
-0.5486376282982826 0.1319280160909472
-0.6290298657976572 0.1311186554658153
-0.7097516324445607 0.1300295771570474
-0.7908582195094479 0.1283401444333144
-0.8726493619315576 0.1255632024232207
-0.9557874491466951 0.121287289782791
-0.998394 0.1185010000000001
0.716234 0.2128159999999999
0.6736308151075925 0.2313316434746808
0.6202156743221956 0.1890656767279146
0.5584101808060664 0.1556812916004489
0.4905933903663739 0.1425176345442529
0.4248133689015459 0.1301033049011176
0.3555687858842773 0.1229314267935583
0.2854567175678533 0.1173306669092046
0.2138422555443553 0.1134465696402275
0.1410000699661211 0.1105988504172902
0.06701232678525826 0.108536822799682
-0.008019751278867449 0.1070103201727947
-0.08396708820864018 0.1058362959012045
-0.1607063909782921 0.1048859470228293
-0.2381107460527406 0.1040793154730518
-0.316075677230921 0.1033731547080745
-0.3945189690023275 0.1027351740666683
-0.4733767880635957 0.1021320636639661
-0.5525981182570584 0.1015136242937724
-0.6321498319057706 0.1007979409516191
-0.7120361320436518 0.09983641327354481
-0.7923627939708733 0.09837350490435359
-0.8734321776868594 0.09604341367403696
-0.9558330887172662 0.09255675724540224
-0.997968 0.09027400000000002
0.6694009999999999 0.218142
0.6668816320575137 0.2155015687713915
0.6079123770016783 0.1457552677555616
0.5450373375852242 0.1283112637641899
0.4808975598866942 0.1104638395303862
0.4140314556828999 0.09966684211347077
0.345170401695458 0.09180007492303416
0.275202261271094 0.08625900942799558
0.2038347101428588 0.08231336318701743
0.1313901455303443 0.07949620754307923
0.05785285548781771 0.0774901405700581
-0.01665127307949532 0.07603260050429839
-0.09202509759987187 0.07492733683746206
-0.1681401285130536 0.07404001107529268
-0.2448787151380758 0.07329391854388112
-0.3221416689803471 0.07265176685001623
-0.3998529954026985 0.07208219531454169
-0.4779540991825709 0.07155502218732723
-0.5563968637389539 0.07102255720545891
-0.6351538884428761 0.07041463839993878
-0.714248131847512 0.06961333169274142
-0.7938116361289399 0.06842280002489198
-0.8741635980076349 0.06658146467647397
-0.9558265326180012 0.06385875116923506
-0.997552 0.06204900000000002
0.6681950000000001 0.180543
0.6505088529378404 0.1518302127496451
0.6003689313808098 0.11826972655124
0.5360766706646221 0.09554576855101221
0.4724347114026639 0.07936079329426077
0.4046900768841488 0.06836091251933346
0.3360814818873239 0.0604998382756714
0.2659456592943683 0.05495246785893654
0.194791624279675 0.05102578260915186
0.1225821438405759 0.04826861599738863
0.04940900709187845 0.04634330389491392
-0.02467519101230253 0.04497030660667456
-0.09956387636887909 0.04394040162282331
-0.1751372566312149 0.04311575583697558
-0.2512806958918591 0.04242896023380194
-0.3279047233271167 0.04184850616861152
-0.4049429693771096 0.04134858139682751
-0.4823419979055947 0.04089845733096503
-0.5600573271188305 0.0404579444540672
-0.6380668647200978 0.03997082155995313
-0.7164055355907457 0.03935326994874155
-0.795225521887465 0.03847198455922818
-0.8748541047936295 0.03714629609658304
-0.9557935459416657 0.03518241063259103
-0.9971410000000001 0.03382299999999999
0.6709780000000001 0.140078
0.6500219677247654 0.1184610222351924
0.5923832625399508 0.08447356684781088
0.5301931244664242 0.06326122432786296
0.464615135280624 0.04756331083659371
0.3968976084947855 0.03674151150305122
0.3278119646226589 0.02894146599142061
0.2576334326531728 0.0234554695657001
0.1865062696344455 0.01959053196307131
0.1144816329572473 0.01692840298041137
0.0415776378241326 0.01510697285973223
-0.03216061844150031 0.01383559128543338
-0.1066432826450989 0.01288495537384921
-0.1817443946040558 0.01212073261006236
-0.2573533774484611 0.01148936183234184
-0.3333948889244223 0.01096875714539997
-0.4098145499007817 0.01053828075119989
-0.486564319362098 0.0101669106830965
-0.563603114106648 0.009822316646416751
-0.6409107674793449 0.009465192543438694
-0.7185286518259452 0.009048565945039222
-0.7966185770773133 0.008501077817745895
-0.8755188951923413 0.007712930468440016
-0.9557373418538672 0.006514167624570966
-0.996719 0.005597000000000019
0.6717500000000001 0.101147
0.646845967298787 0.08000737903841243
0.588594387344971 0.05101079475650022
0.5246861655005794 0.03033784908162201
0.4582204017636626 0.01541989096263069
0.3898270219090596 0.004792225041353737
0.3203670751453387 -0.002837289058502668
0.2500005081412491 -0.008228685278083736
0.178869951996792 -0.01198078632523913
0.1069662484735301 -0.01451985259745664
0.03427807617442435 -0.01620725263895684
-0.03918193678694315 -0.01736205762136644
-0.1133218420800848 -0.01823029371814888
-0.1880068423464684 -0.01893987114026741
-0.2631329675262781 -0.01952161232315197
-0.3386418575907845 -0.01998360879283612
-0.4144929587780762 -0.02034538525027146
-0.4906448676472532 -0.02063649597939166
-0.5670568001078553 -0.02088319364648039
-0.6437078257752729 -0.02110541470992072
-0.7206371759261827 -0.02131214468569026
-0.7980079759783969 -0.02151176501129826
-0.8761695200963563 -0.02174380811249876
-0.9556620059397684 -0.02215966469008357
-0.996306 -0.02262900000000001
0.673451 0.06153799999999998
0.6465295661888188 0.04351795227984345
0.5853636368003965 0.01654191913630187
0.5201587176559446 -0.002858055297465745
0.4524559039995228 -0.01711508353653801
0.3833823503293166 -0.02741901736977137
0.3134721540243188 -0.03484408359808522
0.2429027729117925 -0.04008451796467388
0.1717392614889024 -0.04369069370033341
0.0999363959724977 -0.0460687634004413
0.02742602009563644 -0.04759146382443602
-0.04580508747854661 -0.04861057850075573
-0.1196544418934203 -0.04939803381210556
-0.1939694543487491 -0.0500627436495229
-0.2686538222892053 -0.05060113045937026
-0.3436729054580072 -0.05100633235179602
-0.419002744621836 -0.05129878962167922
-0.4946060915391318 -0.05150898239421453
-0.570440346688839 -0.05165821331307835
-0.6464795077527133 -0.05174514842016797
-0.7227527366302442 -0.05174210819443747
-0.7994127809954346 -0.05159033121618689
-0.8768186724273341 -0.05125163921149117
-0.9555713364203408 -0.0508513933653838
-0.995892 -0.05085499999999998
0.6746330000000003 0.022231
0.6461469276965794 0.006090798217099624
0.5829055921129458 -0.0182323488629838
0.5159465455786236 -0.03641884016192559
0.447054419586199 -0.04996054702822306
0.3772805242621504 -0.05990073342894736
0.3069400218407898 -0.0670619657894278
0.2361770144489628 -0.07211698086420304
0.1649952088368485 -0.07553744214849123
0.09329552063301949 -0.07771644424789736
0.02094845180287863 -0.07903438189816808
-0.05209125083479926 -0.07989693389121433
-0.1256949754879609 -0.08061040843512979
-0.1996729680084657 -0.0812456567333244
-0.2739457816335151 -0.08174789865594789
-0.3485135326945843 -0.08209605401434483
-0.4233663823835907 -0.08231788615590091
-0.4984684747849477 -0.08244758826775583
-0.5737739843699192 -0.08250102112808066
-0.6492469708385948 -0.08245877778807603
-0.7248981275314115 -0.08225475189650006
-0.8008562609841606 -0.08176088268169646
-0.8774812927577973 -0.08084140006484131
-0.9554694909378805 -0.07957707630798239
-0.99547 -0.07907999999999998
0.6763140000000001 -0.01722699999999999
0.6459966858683983 -0.03136649860215557
0.5805180160827705 -0.05337976949666845
0.511623061292668 -0.07024909887363462
0.4417132989832846 -0.08313390463827469
0.3712819620913537 -0.09263422065759469
0.3005921203238568 -0.0994966678438467
0.2296767764437382 -0.1043285390303609
0.1585265440504577 -0.1075276819477602
0.08695941979356325 -0.1094612921400975
0.01478214960678237 -0.1105241137880042
-0.05809872742107147 -0.1112039321844039
-0.1314925955968501 -0.1118610992806052
-0.20515245240728 -0.1124898048532069
-0.2790353952448307 -0.1129614371165099
-0.3531856429759579 -0.1132498213404294
-0.4276037483639491 -0.1133987327045938
-0.5022511277817894 -0.1134484384693495
-0.5770754152919657 -0.1134105474822276
-0.6520296309460857 -0.1132503348937948
-0.7270980296914553 -0.1128644453609882
-0.8023669374767254 -0.1120524550490307
-0.8781788694294368 -0.1105535147672795
-0.9553558562424709 -0.1083534036342335
-0.995061 -0.107306
0.6771320000000001 -0.05657099999999998
0.6462196024823326 -0.06910275081504569
0.5772811058663949 -0.08862575457632732
0.5069532210033583 -0.1044207110097671
0.4360807422844801 -0.1166060935201816
0.3652221094343404 -0.1256397515848274
0.294252401478988 -0.1321409778382737
0.2232739454972592 -0.1367377692603782
0.1522320996214284 -0.1396688409833645
0.0808555306685701 -0.1413084533408634
0.008875135505773901 -0.1420438435857375
-0.06387867664941393 -0.1425095118636777
-0.1370927264477139 -0.1431477960599246
-0.2104368241254188 -0.1438009383537724
-0.2839426433130057 -0.1442434351813762
-0.3577088858282637 -0.1444650621152139
-0.4317331250276428 -0.1445374325541058
-0.5059696328307257 -0.1445085302525065
-0.5803597850404261 -0.1443858233962441
-0.6548443178777817 -0.1441229947316872
-0.7293774872003547 -0.1435862124430649
-0.8039818119460104 -0.1424990630797254
-0.8789405371210903 -0.1404390316469371
-0.9552350677606201 -0.1372118517189856
-0.994638 -0.135532
0.6799820000000001 -0.09608899999999998
0.6441590081955666 -0.1062027383584443
0.5730403404716964 -0.1242365656215098
0.5014284602809682 -0.1388371724794497
0.4300035540567828 -0.150455546152449
0.3589359198508861 -0.1588995331032188
0.2877785773988544 -0.1649965166926952
0.216847731196486 -0.1693740090044583
0.1460299927337756 -0.1719692353728394
0.07491620381567232 -0.1732710804733528
0.003196658840480371 -0.1735680335481081
-0.06947670918787918 -0.1737810198909999
-0.1425376442270292 -0.174474865698277
-0.2155418638246671 -0.1751917578356311
-0.2886827913710682 -0.1755943471784423
-0.362099955278155 -0.1757386821294064
-0.435771889392473 -0.1757301134526084
-0.5096373948204098 -0.1756239032571369
-0.583636923608094 -0.1754248258639142
-0.6577037654871396 -0.1750793977159258
-0.7317581871989611 -0.1744307867709498
-0.8057478707823431 -0.1731381868354858
-0.8798102662010865 -0.1705702237916914
-0.9551113397363029 -0.1661961226236555
-0.994225 -0.163758
0.6740809999999999 -0.135003
0.6390969054778857 -0.1440047394761232
0.5673589701743298 -0.1599483415264623
0.4948666025490549 -0.1736115993138121
0.4233402407177331 -0.1847318834867439
0.3523529693143348 -0.1923837172345134
0.2810077636484749 -0.1980588563874242
0.2103199746244115 -0.2022964105397201
0.1398402049705898 -0.2044184041015036
0.06907449897146223 -0.2053915822760856
-0.002254967420830756 -0.205046605846334
-0.07494235244881675 -0.2049700215094212
-0.1478512158522721 -0.2058639873286096
-0.2204704263263465 -0.2066772916745945
-0.2932632763446649 -0.2070139485260125
-0.3663799880342771 -0.2070641447940256
-0.4397335678622777 -0.2069719631898608
-0.5132656920438778 -0.206789851991055
-0.5869129954811814 -0.2065246611740213
-0.6606082855336408 -0.2061162568871134
-0.7342578449531659 -0.2054068983107971
-0.8077113927927038 -0.2040025478711236
-0.8808701566284403 -0.2010482418115844
-0.954979136676626 -0.195385512588334
-0.993812 -0.191984
0.6678379999999999 -0.174013
0.6327017343775265 -0.1819246524748301
0.5604134553609073 -0.1956997989905994
0.4870038994931216 -0.2087548088386786
0.4161508047242035 -0.2196196141012346
0.3454429291770471 -0.2259361448279211
0.2737520870966175 -0.2313368109020141
0.2036509540286859 -0.2356295097139555
0.1336064940060577 -0.2369398446015281
0.06322475282108653 -0.2377859932696821
-0.007416759503284909 -0.2363784745045339
-0.08032406612207532 -0.2360070117896752
-0.1530514956262202 -0.2373702575735462
-0.2251831013540437 -0.2382784895524746
-0.2977102271137521 -0.2384906203208059
-0.3705628891936708 -0.238437751404776
-0.4436396658833959 -0.2382558791462985
-0.5168618790713837 -0.2380032464853411
-0.590183289895396 -0.2376789621623294
-0.6635554933749778 -0.2372331863409929
-0.7368537595150846 -0.2365074038881504
-0.8099430097551255 -0.2351214822107548
-0.8822083176818615 -0.2320147383508282
-0.9548952330797411 -0.2249188053614931
-0.99339 -0.220209
0.660952 -0.212699
0.6265258960195204 -0.2198195516795895
0.5513817000314682 -0.2309378782961403
0.477893836050941 -0.2447465363005416
0.4086936216677082 -0.2553011025699732
0.3381214426595114 -0.2591537051842576
0.265696862814641 -0.2650164012039838
0.1970852439242929 -0.2695960301390992
0.1271144813754841 -0.2692373384855201
0.05720441254339526 -0.2708587342044957
-0.01210548674715428 -0.2672808414035484
-0.08578183171755704 -0.2668358630713725
-0.1579979317606541 -0.2691220814163444
-0.2296877403655124 -0.2699842082302025
-0.3020309660569004 -0.2700199508977322
-0.3746928700579032 -0.269846644896338
-0.447499213190614 -0.2695815921017914
-0.5204359357871414 -0.2692578966390401
-0.5934452802314611 -0.2688890351646372
-0.6665044213479393 -0.2684158986681954
-0.7395302843111777 -0.2677374141201089
-0.8123805781593834 -0.2664704244039452
-0.8841395209640863 -0.2636732438236563
-0.9547738166488156 -0.2551194747203641
-0.99298 -0.248435
0.656536 -0.252265
0.6167656416865135 -0.255774863024856
0.5403725879743797 -0.266128226110119
0.4678756698443771 -0.2819784125883185
0.4011950394863653 -0.2921694682731505
0.330310803206735 -0.291114459765056
0.2565811849463686 -0.2995676904143368
0.1908993135419297 -0.3046375986693353
0.1202521517565254 -0.3004278135273996
0.05067611440755271 -0.3057427045487291
-0.01603204324181529 -0.2970034362011619
-0.09132930190216915 -0.2975482150370751
-0.1625722858524807 -0.3012943324717113
-0.2339015157666946 -0.3017670872197658
-0.3063698887337452 -0.3015658474230596
-0.3787513782384649 -0.3013021720558607
-0.4513607937697056 -0.3009333242786929
-0.5239896048992818 -0.3005620577976119
-0.59666907082723 -0.3001415220519548
-0.6694620256108966 -0.2996740643215548
-0.7421095413141237 -0.2990636967692806
-0.815023170650384 -0.2980115114817684
-0.8866793098239163 -0.2962141495608518
-0.9552116854994531 -0.2866345453472353
-0.992559 -0.276661
0.639284 -0.287672
0.6018102483907126 -0.2929189603550206
0.5279498580566737 -0.3001107160172192
0.4570116244285602 -0.3228316613121517
0.3956712947273606 -0.3306543521555141
0.3199065727894881 -0.3196707917001717
0.246626836211538 -0.3376742470543756
0.1867491326318125 -0.3412407368401794
0.1117340620647482 -0.3282844151255521
0.04378254773693691 -0.346449331876071
-0.01940915784766584 -0.3232290760405665
-0.09737503711579854 -0.3290360042598662
-0.1655365120464118 -0.3340012463739698
-0.2386522149096787 -0.3334186040029276
-0.3104726283069662 -0.3332159154940674
-0.3829365617259557 -0.3327393573207222
-0.4551789064937278 -0.3323441378480311
-0.5275415462850865 -0.3318881362785149
-0.5998958002177116 -0.3314712625261748
-0.6722379672462478 -0.3309380150367714
-0.7448281409241206 -0.3305951741544386
-0.8167116885416219 -0.3294819791365562
-0.8910791134176194 -0.3296917620398064
-0.9556941362785247 -0.3215688306628628
-0.992143 -0.304887
0.6300399999999999 -0.30512
0.59555 -0.313157
0.5206139999999999 -0.315024
0.458148 -0.347093
0.3882120000000002 -0.349305
0.314263 -0.331354
0.2465360000000001 -0.360349
0.1794149999999999 -0.360358
0.1105320000000001 -0.338293
0.04156500000000007 -0.375299
-0.02392399999999995 -0.331503
-0.09672599999999998 -0.34723
-0.168308 -0.349672
-0.240671 -0.34957
-0.312765 -0.348901
-0.384972 -0.348533
-0.457132 -0.348041
-0.529309 -0.347582
-0.601485 -0.347155
-0.673645 -0.346615
-0.745851 -0.346355
-0.817947 -0.34543
-0.890299 -0.346056
-0.962083 -0.343037
-0.99194 -0.319
</coefs>
 </Geometry>
 <MultiPatch parDim="2" id="1">
  <patches type="id_range">0 0</patches>
  <boundary>0 1
0 2
0 3
0 4
</boundary>
 </MultiPatch>
</xml>
