<?xml version="1.0" encoding="UTF-8"?>
<!--This file was created by G+Smo 21.12.0-->
<xml>
 <Geometry type="TensorBSpline2" id="0">
  <Basis type="TensorBSplineBasis2">
   <Basis type="BSplineBasis" index="0">
    <KnotVector degree="2">0 0 0 0.043478 0.08695700000000001 0.130435 0.173913 0.217391 0.26087 0.304348 0.347826 0.391304 0.434783 0.478261 0.521739 0.565217 0.608696 0.652174 0.695652 0.73913 0.782609 0.826087 0.869565 0.913043 0.956522 1 1 1 </KnotVector>
   </Basis>
   <Basis type="BSplineBasis" index="1">
    <KnotVector degree="2">0 0 0 0.043478 0.08695700000000001 0.130435 0.173913 0.217391 0.26087 0.304348 0.347826 0.391304 0.434783 0.478261 0.521739 0.565217 0.608696 0.652174 0.695652 0.73913 0.782609 0.826087 0.869565 0.913043 0.956522 1 1 1 </KnotVector>
   </Basis>
  </Basis>
  <coefs geoDim="2">0.8824400000000001 0.8849800000000001
0.8308490000000002 0.8729080000000002
0.726213 0.856006
0.6250220000000002 0.8233050000000002
0.5286280000000001 0.7835060000000003
0.434574 0.7253620000000001
0.350614 0.6809920000000003
0.2618510000000001 0.575448
0.2159679999999999 0.6294899999999999
0.1842360000000001 0.7459010000000004
0.1337189999999999 0.834417
0.07381200000000021 0.9203680000000003
0.0005790000000001072 1.009256
-0.07586899999999996 0.9217820000000001
-0.136276 0.837019
-0.186734 0.747781
-0.218646 0.632479
-0.2660290000000001 0.5751510000000002
-0.3550450000000001 0.6818470000000001
-0.438921 0.725627
-0.533077 0.7838510000000001
-0.6294729999999999 0.823698
-0.730707 0.855904
-0.83526 0.8737520000000001
-0.88706 0.8835900000000003
0.8720220000000001 0.833129
0.8286610637594203 0.8301666848274618
0.7311461736724851 0.8148201362698775
0.633878800413795 0.7873445886955506
0.5393534808994223 0.7501559033125196
0.4467078119770014 0.7000954931399721
0.364020018258657 0.6531806629420789
0.2732333061975989 0.574808644877197
0.2066675209596065 0.6014448742222347
0.1644361914360755 0.7066995443790285
0.1182713135064126 0.7902322805392796
0.05841349644007043 0.8702538339106989
-0.001045813910422577 0.9167790708207921
-0.06066414751246851 0.8719924129481829
-0.1206991546684139 0.7922504306368674
-0.1669184868269358 0.708762265133446
-0.2095515037878882 0.603234198399456
-0.2771279589819281 0.5746341482715971
-0.3682919009988397 0.6536551067921621
-0.4509250647753141 0.7003579880353865
-0.5437296544925518 0.7504368912218673
-0.6381143467992574 0.7875446133448702
-0.7355166613826921 0.8148140462124331
-0.8323333393976611 0.8302057285762625
-0.874991 0.8320209999999999
0.8543960000000002 0.7284820000000001
0.8132851454315733 0.7332259947132542
0.72591602674227 0.7276009166272916
0.6358112931333468 0.7084584515913164
0.5465102961539354 0.6786781741493435
0.4595125855699365 0.6401237449641859
0.3766396730882882 0.5977047824828743
0.2945090136694859 0.5537972892212306
0.2131097431469477 0.5594687250282717
0.1501138731288121 0.6158094650253203
0.1005042890188617 0.6833511467997271
0.05016731191186352 0.7327639174694736
-0.001285503969320478 0.7531177775146511
-0.05277996600089507 0.7335670467997937
-0.1031786527452385 0.6845695369827784
-0.1529952635563689 0.617057448909335
-0.2162928584668801 0.5602948070398572
-0.2980996465178943 0.5538523844126719
-0.3806263908855908 0.5978979451644357
-0.463540624607477 0.6403171923259678
-0.5505835880445076 0.6787821438073236
-0.6398542775235363 0.7084903745071822
-0.7298184048627738 0.7273938255741392
-0.81694900604382 0.7325025106102825
-0.8581029999999999 0.7274290000000001
0.8220559999999999 0.627143
0.7859551032181924 0.6358118594383562
0.706951227811826 0.6375811446385959
0.624600590059986 0.6261999335881165
0.5415682732495768 0.6040252178037808
0.4600093509138736 0.574621814381657
0.3810595919556476 0.5422945423908476
0.301941058433991 0.5171779106899379
0.2256370756662891 0.5183214484528522
0.1570501552154289 0.5446474822272558
0.09854988703820222 0.5826669561328359
0.047497752725145 0.6138105253951505
-0.001508210960015299 0.6256997062758922
-0.05052225055131909 0.6142301898789899
-0.1016396409836309 0.5833296888807418
-0.1602214278191044 0.5453684183215712
-0.228934774843049 0.5188416682974797
-0.3054725418239433 0.5173710941490517
-0.3847957414176233 0.5424192512283206
-0.4638514521446834 0.5747280002889363
-0.5454260458827084 0.604050209599166
-0.628413646694278 0.62609237515891
-0.7106129682924606 0.6372423743670532
-0.7894306128838263 0.6352252087226207
-0.8253509999999999 0.626295
0.7821740000000001 0.5306740000000001
0.7487934119415671 0.5413358666210726
0.6772075278303307 0.5482641213724258
0.6025108511602777 0.5431768089661111
0.5267837506109616 0.5283041619910831
0.4518289051361097 0.5073901820952618
0.3779539103677216 0.4860155355601967
0.3047782907830365 0.4718420814011017
0.2330733656947745 0.4715048350612623
0.1662675000223932 0.4848274641370391
0.1056052636109772 0.5045097789455424
0.05032100234034798 0.521433463086868
-0.001636433391094094 0.5281390528864112
-0.0536022977434949 0.5216801145448708
-0.1088966893410626 0.5049351912987268
-0.1695926923576394 0.4852968666052462
-0.2364642678055069 0.4718884267936141
-0.3082701598724368 0.4720774201154758
-0.381565180667531 0.4861630013528133
-0.4555133533790184 0.5074743645292572
-0.5304954511884721 0.5283001790893433
-0.6061866732489594 0.543039583559533
-0.6807991519484382 0.5479286295579693
-0.7522201957467223 0.5407054481816023
-0.78555 0.5299580000000002
0.723903 0.4364360000000003
0.6986635868071023 0.448484824308369
0.6386810179311468 0.4611961115002461
0.5731449978054157 0.4615790427201596
0.5059188301672661 0.453310661971053
0.4389364020103135 0.440377175303746
0.3719522437559681 0.4278597988031925
0.3044077966780951 0.4198977943687083
0.2372815082138533 0.4193733966892406
0.172338930108292 0.4260064358964339
0.1111714122121021 0.4364946294235916
0.05368132757818467 0.4456348835827539
-0.001706014814699452 0.449249952986573
-0.05709266468546326 0.4457983921798783
-0.1145845093352912 0.4367769871734242
-0.1757607580729642 0.4263367766406547
-0.240726124502222 0.4196777978227864
-0.3079003345449361 0.4201350366149483
-0.3754964944965713 0.428030858467491
-0.4425295671066424 0.4404868361436038
-0.5095392355538509 0.4533400717870297
-0.576750640945189 0.4614809317298123
-0.6422204500356783 0.4609457275026563
-0.7021640325498724 0.4480963347527518
-0.727414 0.435937
0.6799500000000001 0.3525130000000001
0.6518834020081732 0.3658546442685215
0.5962324186576358 0.3782506198874402
0.5408115889710934 0.3825228987515317
0.4845739532915756 0.379375659518036
0.4264438948371256 0.3733602651981838
0.3657527655835238 0.3671615391263219
0.3029095009816984 0.3631840701875735
0.2391408824672447 0.3629389463168251
0.1761150540583016 0.3664562399247271
0.1149623985737858 0.3719620708264642
0.05592257073670504 0.3768655863201085
-0.001747772493315258 0.3788468176331123
-0.05941494920625356 0.3769761625984032
-0.1184503149361723 0.3721588546039643
-0.179598694358973 0.3666967576513562
-0.242628437279687 0.3631804878933333
-0.3064065818421182 0.36339950616241
-0.3692695517370909 0.3673417856279451
-0.4299845748019305 0.3735066083224534
-0.4881446513451154 0.3794723930247517
-0.54441231667449 0.3825396462415667
-0.5997978273915727 0.3780899728148666
-0.6552418688680806 0.3654652606103668
-0.683044 0.3520520000000003
0.5732750000000002 0.263447
0.572833546439431 0.2745340450060123
0.5521831028142135 0.2957311579225048
0.5157352712456442 0.3032413034764838
0.470452014887502 0.306123342630072
0.4185105062692356 0.3057992737583344
0.3617759013551043 0.3043270520511958
0.301781169735682 0.3032213652433058
0.2401464618553746 0.303626389054193
0.1783154892492727 0.3057442957256256
0.1172962490145071 0.3088217740313051
0.05738690781439559 0.3114997762507603
-0.001776212551235723 0.3125756416281744
-0.06093631858449866 0.3115761919075268
-0.1208380437393343 0.3089591373994343
-0.1818470704044404 0.3059190866477552
-0.243667152971207 0.3038127365922119
-0.3052934582337412 0.3034014732429657
-0.3652796154495652 0.3044992421959472
-0.422011055559451 0.3059669111695396
-0.4739661324456018 0.3063043946884563
-0.5193048804494826 0.3034335953210181
-0.5559118940563819 0.2959605808773493
-0.576884411219093 0.2746445570702221
-0.5774999999999999 0.2632860000000004
0.631316 0.2164409999999999
0.6017641136171783 0.2072464183139977
0.5586251762610717 0.2140771345266179
0.5171695743238269 0.2268093077452202
0.4702137253815866 0.2343901332821821
0.4180107936976627 0.2386776921577072
0.3615208989438341 0.2405868033478709
0.3021627084640788 0.2416223939794664
0.2412471161858449 0.2427522366202874
0.1798913826985136 0.2443826277379519
0.1188241518589213 0.2462720390000708
0.05830900340474066 0.2478235851582846
-0.001798905374288617 0.2484411312834405
-0.06190443076176233 0.2478750065810538
-0.1224108918543566 0.2463663708799828
-0.1834656426691224 0.2445041487155784
-0.2448047091252361 0.2428864020172268
-0.3056990005962081 0.2417603532711894
-0.3650304245001152 0.2407283703906382
-0.4214824978821216 0.2388412501665356
-0.4736311510275867 0.2346053998125475
-0.5204690964327791 0.2271384922379631
-0.5616514526802844 0.2145860207778763
-0.603742115991279 0.2081411615678239
-0.6319189999999999 0.2174880000000001
0.746764 0.1845300000000001
0.7072685647036816 0.164851303556284
0.6153227098081864 0.1509398773665516
0.5435872662750978 0.1582328229381822
0.4835572086782236 0.167610164644951
0.4246201580849027 0.1737747688864117
0.3650026344950283 0.1775996220118952
0.304241587436068 0.1798317409785632
0.2428427560161126 0.1814327972312619
0.1812847579104511 0.1828533083380834
0.1199426545161215 0.1841544776612498
0.05894219079720764 0.1851151382206984
-0.001819303238928427 0.1854839019526104
-0.06257814399081763 0.185148177995895
-0.1235723162041217 0.1842145463389264
-0.184902871201108 0.182931538907783
-0.2464450163644328 0.1815189845286285
-0.3078210537684055 0.1799208762171214
-0.3685481550966945 0.1776968430047865
-0.4281148276521334 0.1738968087372559
-0.4869571037549955 0.1678014939397237
-0.5468067030086861 0.1585612091413482
-0.6180356464307989 0.1516135560095719
-0.708985154343168 0.1659566270999127
-0.748146 0.1857440000000001
0.8356550000000003 0.1340669999999999
0.7908582329516838 0.1187980411013836
0.6826040538428628 0.1013585022892565
0.5814449750857884 0.09976373584074194
0.5031210935264614 0.1070112455290293
0.4350209616122898 0.112658328073441
0.3704372417526793 0.1164942709654362
0.3072623917951913 0.1188504004029356
0.2446881431959798 0.1203961531450428
0.1825531595927656 0.1215333289517395
0.1208032534914754 0.1224156274311712
0.05938583964944466 0.1230125302733232
-0.001838096555470736 0.1232314899161973
-0.06306092937645591 0.1230319949059648
-0.1244748432545277 0.1224503080076298
-0.1862188645466811 0.1215758380923588
-0.2483449708149364 0.1204395674648662
-0.3109047321830531 0.1188919942992632
-0.3740570228400489 0.1165374014991327
-0.4386044213535613 0.1127257114334121
-0.5066379376255453 0.1071404979124766
-0.5848281050900519 0.1000685086797461
-0.6855482927244447 0.1020190691475542
-0.7924511150284469 0.1197682690633453
-0.836661 0.1352300000000002
0.9214169999999999 0.0729700000000002
0.8697082357682879 0.0589352475946221
0.7315647114423871 0.05119173309245117
0.6122735331004039 0.04876703903367563
0.5198557728325042 0.05179310163200967
0.4440327200060423 0.05522246186705493
0.3752475810861924 0.05749770276000254
0.3098715354135231 0.0589746578764152
0.24618928025203 0.05990428580630991
0.1834777559286611 0.06054664336286097
0.121375248617309 0.06100369009439199
0.05966039261205314 0.06129527796376766
-0.001855193577134262 0.06140106746623397
-0.06337156331868721 0.06130518652448846
-0.1250872802116033 0.06101985987626213
-0.1871924586058915 0.06056236272779558
-0.2499060458251501 0.05991307539677337
-0.3135898502977238 0.05897329531847961
-0.3789654887104275 0.0574904470780726
-0.4477461741094925 0.05523204944962301
-0.5235601904008973 0.05185598794904323
-0.6159569665689217 0.04902402092202252
-0.7349431787435441 0.05168078828331812
-0.8724827049908579 0.05993086276961113
-0.922569 0.07537299999999991
1.009792 0.001371999999999929
0.9150021424270056 -0.0001787254792913195
0.7513353537193461 -0.0001042156072266209
0.6239022603595339 -0.0001282783100562401
0.5263939186622708 -0.0001062879889597301
0.4475245681283146 -0.0001087660166079196
0.3771367914538413 -0.0001339997676566007
0.310878318998675 -0.0001625245300260758
0.2467566589405672 -0.0001892190902095248
0.1838111405203482 -0.0002092115621239454
0.1215691168253996 -0.0002211117300907617
0.05974815674065148 -0.0002261903322926528
-0.001869726364518653 -0.0002256095898554022
-0.06348969942861571 -0.0002214231393051769
-0.1253174252973429 -0.0002161293914564322
-0.1875705201461477 -0.0002106834582318307
-0.2505317477129176 -0.000205263556861679
-0.3146729157023996 -0.0001986811075940231
-0.3809522764332074 -0.0001860458767342088
-0.4513650200830671 -0.0001599251784545341
-0.5302626674722233 -0.0001004444386945025
-0.6278335638461906 1.908326001265337e-05
-0.755266231434613 0.0002426238962418559
-0.9189721016567909 0.0004554384536763489
-1.011374 0.002091999999999983
0.920714 -0.07336399999999998
0.8701252813638807 -0.05924511617911865
0.731591109223122 -0.05140244547571537
0.6123694778090194 -0.04903559587283501
0.5198468877044999 -0.05197832929852253
0.4439845653652392 -0.05543808507883807
0.3751930249654387 -0.05776564907694703
0.3098212642538374 -0.05930572489743391
0.2461480239473766 -0.06028983789752684
0.1834449768168727 -0.0609715851940722
0.121348038208495 -0.06145199414324964
0.05963627717198428 -0.06175134533040227
-0.001880230447576237 -0.06185375452866226
-0.06340029092562061 -0.06174799090627237
-0.1251240371370324 -0.06144983343875354
-0.18724073936219 -0.06098019669872057
-0.2499715347271283 -0.06032001016108068
-0.3136794748415844 -0.0593661837666869
-0.379088170870688 -0.05785970402101714
-0.447919363814458 -0.05555039289928732
-0.5238035034089958 -0.05207055223014301
-0.6163543998731038 -0.04898847736909251
-0.7356857234661789 -0.05125145741891046
-0.874116993114085 -0.05914010822679017
-0.9238229999999999 -0.07443599999999984
0.8364560000000001 -0.134476
0.7909891689047066 -0.1189243294884601
0.6828252089968514 -0.1017057543370687
0.5815712970200657 -0.09995128304807521
0.5030595542033616 -0.1071525228746589
0.4349167789610628 -0.112861044522876
0.3703248440799642 -0.1167691607106898
0.3071654972929443 -0.1191995418569783
0.244609371413679 -0.1208034833058134
0.1824903477209276 -0.1219800525163168
0.1207516678611538 -0.1228812996290328
0.0593395182641927 -0.1234803622877789
-0.00188557383313559 -0.1236894220146068
-0.06311595177259544 -0.1234732247657691
-0.1245439705214875 -0.1228737402729176
-0.1863093077403489 -0.121983690910395
-0.2484657530391119 -0.1208346518905921
-0.3110667139136702 -0.1192745128350159
-0.374277073353381 -0.11689997051086
-0.4389044125317928 -0.1130476028581696
-0.5070697335721136 -0.1073704794295028
-0.5854483618840319 -0.1001131407955019
-0.6866870060533029 -0.1016328411741365
-0.7943363545460311 -0.1191797702115801
-0.839113 -0.1347240000000001
0.746523 -0.1845649999999999
0.7076428942310167 -0.1654581695087008
0.6157139272627974 -0.1511599009096707
0.5435578005218513 -0.1582597797336874
0.4834074986969568 -0.1677017992707717
0.4244423284137684 -0.1739669214159917
0.3648401216389527 -0.1778962974679925
0.304106195990137 -0.1802152091186822
0.2427344483845699 -0.181879632521732
0.1811984449056738 -0.1833372208446971
0.1198715301171713 -0.1846502499224284
0.05887721365444154 -0.1856029759490818
-0.001885619282581574 -0.1859502116158787
-0.06265473436581026 -0.1855872747772483
-0.123666894388766 -0.1846271861800765
-0.1850245487641801 -0.1833229670858063
-0.2466029199752218 -0.1818964706289511
-0.3080276522261916 -0.1802889564339603
-0.3688183958375139 -0.1780527933719354
-0.4284728194386548 -0.1742282123699023
-0.4874440883543681 -0.1680732825015561
-0.5475169475922175 -0.1587101670173227
-0.6191708031553322 -0.1514628802828264
-0.7108848187721968 -0.1653455530707421
-0.749919 -0.185226
0.6324190000000001 -0.217514
0.6022525725444592 -0.2075011128106083
0.5584712078400214 -0.2138941727416926
0.5169128631893478 -0.2266744754921316
0.4699501878555772 -0.2344421534593798
0.4177780058805447 -0.238883287410919
0.3613270571554759 -0.2409245827790282
0.3020055514038857 -0.2420601073306946
0.2411217580205967 -0.2432575092310187
0.1797899907729859 -0.2449209210567818
0.1187379244393338 -0.2468124525250172
0.05822977052640232 -0.2483402681153305
-0.001881368122384597 -0.2489191653306392
-0.06199781710138341 -0.2483099167857361
-0.1225241493378703 -0.246762626821163
-0.1836062213056673 -0.2448737489164176
-0.2449803402690444 -0.2432424087722429
-0.305917807969476 -0.2421133541460128
-0.3653013235557574 -0.2410849338081633
-0.4218171291120617 -0.2391964142861789
-0.4740476143470863 -0.2349496529687976
-0.5210184735591983 -0.2274393724295503
-0.562481506786106 -0.2147999268006567
-0.6053868739521586 -0.2080040463990492
-0.6346079999999999 -0.2170169999999999
0.5720860000000001 -0.262284
0.5718333942965563 -0.27324878203757
0.551570362279681 -0.2950544715354583
0.5153256800723514 -0.3030189572538056
0.4701428998403241 -0.3061628411276561
0.4182697263747543 -0.3060436811095758
0.3615832660193254 -0.3047246758089218
0.3016257384623295 -0.303732656356293
0.2400173093067441 -0.3042095028989079
0.1782056304769331 -0.3063564482539294
0.1171979531703931 -0.3094210309963705
0.05729199814824137 -0.3120550512840665
-0.001875075678294369 -0.3130682806109588
-0.06104714665371369 -0.312003325828886
-0.1209666783963544 -0.3093331652348016
-0.1819983840954198 -0.3062595647089715
-0.2438447533324749 -0.3041435546256814
-0.3054981801465458 -0.3037431080313666
-0.3655130254352843 -0.304863593096412
-0.4222695754647401 -0.3063689491919672
-0.4742351482878467 -0.3067569615404004
-0.5195541805293226 -0.3039836458610433
-0.5560688878915732 -0.2966573284754302
-0.5768980440505523 -0.2757511954091888
-0.577433 -0.264643
0.678383 -0.3515029999999999
0.6507284785669236 -0.3651112166024859
0.5955506938458712 -0.3776766174331733
0.540398967093523 -0.3822713756256115
0.4843053136089672 -0.3794346069407082
0.4262514971854252 -0.3736529072052817
0.3656014848475724 -0.3676310082277956
0.3027774382062227 -0.3637819086746984
0.2390189980444331 -0.3636182237853471
0.1759974553241048 -0.3671617131630448
0.1148461468101265 -0.3726390081626472
0.05580322502278978 -0.3774688767534154
-0.00187358416356509 -0.3793549131488096
-0.05955161412548926 -0.3773903151087566
-0.1185994700129153 -0.3724988776327031
-0.1797607545209742 -0.3669992645748528
-0.2427987700733861 -0.363482992094607
-0.3065819058751122 -0.3637311005026023
-0.369442407318025 -0.3677234854281302
-0.4301516170818682 -0.3739595026357606
-0.488305308051338 -0.380045721550833
-0.5445856102536522 -0.3833052021178635
-0.6000974735661018 -0.3791692066993581
-0.6559091787397202 -0.3668565309242945
-0.684155 -0.353644
0.7229040000000002 -0.435173
0.6978072346520794 -0.4475021149162558
0.6380676876407509 -0.4606699349387497
0.572803459196471 -0.4613773186396564
0.505755582825032 -0.4534130684437583
0.4388499234954446 -0.4407274856638606
0.3718818235231769 -0.4284002852343287
0.3043215409131776 -0.4205865907263179
0.237167814671168 -0.4201648467425984
0.1722017934538984 -0.4268298352724619
0.1110158730432513 -0.4372681205342976
0.05351037617426324 -0.4463008550915546
-0.001885611768855044 -0.4497734947550711
-0.05728038282407844 -0.4461844032362887
-0.1147725618617725 -0.4370664051580113
-0.1759434395410432 -0.4265844324150503
-0.2408924369100818 -0.419945510485365
-0.3080315861862442 -0.420462118872587
-0.3755892165341714 -0.4284298601613419
-0.4425891576718867 -0.4409799258008509
-0.5095974128743253 -0.4539811136437145
-0.5768779633476848 -0.4623464827247546
-0.6425032461521942 -0.4620658585399808
-0.7025746748791455 -0.4494844967024635
-0.727863 -0.4374990000000001
0.7812190000000001 -0.529393
0.7480172433801846 -0.5402568385134185
0.6768467853260354 -0.5477591672848712
0.6023874017427893 -0.5430923772470619
0.5268157849303789 -0.5285097049192402
0.4519217704582341 -0.5078239798343072
0.3780209484219677 -0.4866245173612811
0.304758152273404 -0.472610325115037
0.232956258185778 -0.4724257955490416
0.1660739396367905 -0.4858029830066384
0.1053564700038754 -0.5054228277273939
0.05004376981229886 -0.5221707208990318
-0.001935356715371261 -0.5286718315768899
-0.05389025244392809 -0.5220192596942107
-0.1091708488966601 -0.5051310971425482
-0.1698261917815105 -0.4854594701188021
-0.2366329599649759 -0.4721103079366851
-0.3083465021453557 -0.4724114506233451
-0.3815365873181256 -0.4865736217383618
-0.4554230806898023 -0.5079688770942086
-0.5304036284832202 -0.5289422145083247
-0.6061795895349845 -0.5439013839801332
-0.6809384608255755 -0.549092148741178
-0.7526360270038519 -0.5422736375098949
-0.786058 -0.5316149999999999
0.8211700000000002 -0.625761
0.7853984911487129 -0.6349570102405115
0.7068030826881826 -0.6372754714125527
0.6247613967605361 -0.6263133846548885
0.5418724324398849 -0.6044198408952852
0.4603546604018991 -0.5752055472733087
0.3813420377692995 -0.5429884038328474
0.3020294820007587 -0.5179943926354655
0.225483683239257 -0.5194170429242153
0.156726442405168 -0.54584897458565
0.09810095481236791 -0.5837426273169436
0.04696228620173426 -0.614691808715508
-0.00203599361103457 -0.6262406198086397
-0.05103941009713053 -0.6144408925003756
-0.102076089340542 -0.5833797322790438
-0.1605604269868495 -0.5453697107545875
-0.2291334723500308 -0.5189814213379864
-0.3054547337831334 -0.5177345761095459
-0.3845892718086054 -0.5428149758282244
-0.4635490905767522 -0.5751536542000024
-0.5451211337198214 -0.6046071995994587
-0.6281959045599868 -0.6268624065896699
-0.7106348594111627 -0.6383422514377332
-0.7897179394474513 -0.6366085151608185
-0.825914 -0.627982
0.8541840000000001 -0.727001
0.8131357511364536 -0.7324414396035501
0.7261907123246278 -0.7276692475729004
0.6363322866965628 -0.7089338397214444
0.5471269338530573 -0.6793027245431893
0.4601224390053289 -0.6409407445217399
0.3772394924249967 -0.5985899941299753
0.294769554993715 -0.5545956350832846
0.2128434577695906 -0.5608661864200706
0.1494430817929047 -0.617390460048184
0.09959584372992336 -0.6849280415386492
0.04924982343248097 -0.7339648410913411
-0.002242711781962337 -0.7536754804738692
-0.05365767423080015 -0.7335051045257577
-0.1039961990232889 -0.6841890247149688
-0.1535834527251941 -0.6167364247182042
-0.2165527695890523 -0.5602392436478743
-0.2979533482288238 -0.5542989477328093
-0.3801490608490654 -0.5981754949894423
-0.4629991361918445 -0.6405972424681576
-0.5499765968452837 -0.6791881157816955
-0.63930384805879 -0.7090230292545054
-0.7294927780417306 -0.7282760403136528
-0.8169571786256526 -0.7340411680852643
-0.858009 -0.729156
0.8710760000000002 -0.831727
0.8285983895963132 -0.8307029784419657
0.7320507735713877 -0.815334931001878
0.6345988281825337 -0.7881520604871091
0.5403224184576265 -0.7511296390221756
0.4475625319617711 -0.7010958205313422
0.3649092318143914 -0.6544961788788868
0.2739142386336098 -0.5755293613692188
0.2059591169132537 -0.6036339076821027
0.1632517882876503 -0.7090550501846986
0.1171962519616723 -0.7924953519073209
0.05716651245748605 -0.8723139546997836
-0.002373812020519228 -0.9174212582805604
-0.06187324586327492 -0.8711939940771756
-0.121701191913356 -0.7912137958483423
-0.1679231350362178 -0.7078554768735696
-0.2100731698807576 -0.6025823441555147
-0.2766534769108928 -0.575197462157387
-0.3675545725227564 -0.6536138532183007
-0.4501235189363689 -0.7005189953782793
-0.5427001982319648 -0.7505712404345656
-0.6372044572304127 -0.7877857073862046
-0.7344866648305541 -0.8153504388009505
-0.8323556138079711 -0.8307589309578918
-0.876095 -0.833688
0.88317 -0.88337
0.831577 -0.8747239999999999
0.727052 -0.856393
0.6259540000000001 -0.82443
0.529614 -0.784581
0.4355609999999999 -0.726417
0.35171 -0.682799
0.262758 -0.5760999999999999
0.214842 -0.6327289999999999
0.1832119999999999 -0.7481389999999999
0.1326909999999999 -0.83729
0.07256300000000016 -0.921868
-0.003994000000000053 -1.009775
-0.07731199999999994 -0.921393
-0.1371669999999999 -0.835459
-0.187719 -0.746982
-0.2194469999999998 -0.6310559999999998
-0.265366 -0.575775
-0.354151 -0.681451
-0.4379469999999999 -0.725746
-0.531927 -0.783895
-0.6282 -0.82367
-0.729263 -0.856484
-0.8338 -0.873349
-0.88534 -0.88542
</coefs>
 </Geometry>
 <MultiPatch parDim="2" id="1">
  <patches type="id_range">0 0</patches>
  <boundary>0 1
0 2
0 3
0 4
</boundary>
 </MultiPatch>
</xml>
