<?xml version="1.0" encoding="UTF-8"?>
<!--This file was created by G+Smo 23.12.0-->
<xml>
 <Geometry type="TensorBSpline2" id="0">
  <Basis type="TensorBSplineBasis2">
   <Basis type="BSplineBasis" index="0">
    <KnotVector degree="2">0 0 0 0.5 1 1 1 </KnotVector>
   </Basis>
   <Basis type="BSplineBasis" index="1">
    <KnotVector degree="3">0 0 0 0 0.003 0.006 0.006 0.006 0.2071 0.4082 0.4082 0.4082 0.4485 0.4888 0.4888 0.4888 0.4944 0.5 0.5 0.5 0.5056 0.5112 0.5112 0.5112 0.5515 0.5918 0.5918 0.5918 0.7928999999999999 0.994 0.994 0.994 0.997 1 1 1 1 </KnotVector>
   </Basis>
  </Basis>
  <coefs geoDim="2">
   0.03 0 
   0.04125 0 
   0.06375 0 
   0.075 0 
   0.03 9.999999999999998e-05 
   0.04118209533798621 4.269764263813004e-05 
   0.06375540965611634 0.0001260986342396985 
   0.075 0.0001333333333333333 
   0.03 0.0002833333333333333 
   0.04104652809743929 0.0001366667648123468 
   0.06376442673160483 0.0003719284365556423 
   0.075 0.0004 
   0.03 0.0004333333333333333 
   0.04091106928678962 0.0002478609312993213 
   0.06377027788244299 0.0006052780173942581 
   0.075 0.0006666666666666665 
   0.03 0.0004999999999999999 
   0.04084328187212491 0.0003079859210222251 
   0.06377244795942455 0.0007187246659238643 
   0.075 0.0007999999999999998 
   0.026 0.0004999999999999999 
   0.03834711170560027 0.008637769358125944 
   0.06279977622264751 0.005275955154656869 
   0.07489999999999999 0.0106 
   0.018 0.0004999999999999999 
   0.03103649218111277 0.01267394260896618 
   0.06039384402703967 0.02002109363273422 
   0.07136666666666668 0.02886666666666667 
   0.009999999999999998 0.0004999999999999999 
   0.0258199790833754 0.01761267150441786 
   0.05396242967945417 0.02805542989518174 
   0.06116666666666667 0.04446666666666667 
   0.005999999999999999 0.0004999999999999999 
   0.0243110923686277 0.02116942746962078 
   0.05012917782235805 0.02985635507902834 
   0.05440000000000001 0.0516 
   0.0052 0.0004999999999999999 
   0.02402281104859345 0.02158874665539448 
   0.04913379609283475 0.03101719679985426 
   0.05306666666666668 0.0503 
   0.003599999999999999 0.0004999999999999999 
   0.02352582421408104 0.02235284935753457 
   0.04694607703803603 0.03359065230853709 
   0.05038333333333335 0.04771666666666668 
   0.001999999999999999 0.0004999999999999999 
   0.02339568256823479 0.02311799356010108 
   0.04391194719639623 0.03642069163063349 
   0.04766666666666668 0.04516666666666667 
   0.001199999999999999 0.0004999999999999999 
   0.02322687497697137 0.02290850072780854 
   0.04216166663036423 0.03964677862846398 
   0.04630000000000001 0.0439 
   0.001066666666666666 0.0004999999999999999 
   0.02324748241982329 0.02296872902691565 
   0.04190475199624972 0.03982443051307046 
   0.04610000000000002 0.04410000000000001 
   0.0008166666666666658 0.0004999999999999999 
   0.02327360121551666 0.02308813700221673 
   0.04141295275101425 0.04018661713133922 
   0.04570000000000001 0.0445 
   0.0005999999999999991 0.0004999999999999999 
   0.02326903256921352 0.02320806181659975 
   0.04096429011627162 0.0405585059204072 
   0.04530000000000002 0.0449 
   0.000499999999999999 0.0004999999999999999 
   0.02325899253041447 0.02326874888142028 
   0.04075038608117199 0.04074619140717883 
   0.04510000000000002 0.0451 
   0.000499999999999999 0.0006000000000000008 
   0.0231983508359994 0.02327889325393628 
   0.04056267931680356 0.04095995150336885 
   0.04490000000000002 0.0453 
   0.000499999999999999 0.0008166666666666676 
   0.02307869605613579 0.02328342845694916 
   0.04019029830952393 0.04140894681282661 
   0.04450000000000001 0.0457 
   0.000499999999999999 0.001066666666666668 
   0.02295932213659566 0.02325746862685559 
   0.03982816217255176 0.0419004240452326 
   0.04410000000000001 0.0461 
   0.000499999999999999 0.0012 
   0.02289928053906592 0.02323682944711694 
   0.03965029783026056 0.04215745295842336 
   0.04390000000000003 0.04629999999999999 
   0.000499999999999999 0.002 
   0.0231093750720788 0.02340542506619922 
   0.03642237419544435 0.04390833079536588 
   0.04516666666666669 0.04766666666666666 
   0.000499999999999999 0.0036 
   0.02234501156920217 0.02353510445671873 
   0.03359240801046869 0.04694365264152912 
   0.04771666666666668 0.05038333333333333 
   0.000499999999999999 0.0052 
   0.02158162245474763 0.0240316816238604 
   0.03101849366963644 0.04913150486370689 
   0.05030000000000003 0.05306666666666666 
   0.000499999999999999 0.006 
   0.02116253924729727 0.02431965174255354 
   0.02985769731290652 0.05012719174111339 
   0.05160000000000002 0.0544 
   0.000499999999999999 0.01 
   0.01760792364781542 0.025827654890746 
   0.02805621248812507 0.05396149441220453 
   0.04446666666666669 0.06116666666666666 
   0.000499999999999999 0.018 
   0.01267139478313561 0.03104031766113602 
   0.02002095803489079 0.06039411106179686 
   0.02886666666666669 0.07136666666666666 
   0.000499999999999999 0.02599999999999999 
   0.008636677635676382 0.0383482341436771 
   0.005275077046888187 0.06280009167198508 
   0.01060000000000002 0.07489999999999999 
   0.000499999999999999 0.02999999999999999 
   0.0003079130612346549 0.04084332411211793 
   0.0007187239658829143 0.0637724634722419 
   0.0008000000000000213 0.075 
   0.0004333333333333323 0.02999999999999999 
   0.0002478076246502172 0.04091111761787418 
   0.0006052640909158523 0.06377026151733577 
   0.000666666666666688 0.075 
   0.0002833333333333324 0.02999999999999999 
   0.0001365989552934023 0.04104656516519222 
   0.0003719613183160839 0.06376440980008045 
   0.0004000000000000214 0.075 
   9.999999999999906e-05 0.02999999999999999 
   4.268246852770482e-05 0.04118209868557699 
   0.0001261047830774909 0.06375541277000084 
   0.0001333333333333547 0.075 
   -9.328909172934272e-19 0.02999999999999999 
   -1.952532464414661e-18 0.04125 
   9.180265055086512e-18 0.06375 
   2.133270412170892e-17 0.075 
  </coefs>
 </Geometry>
 <MultiPatch parDim="2" id="1">
  <patches type="id_range">0 0</patches>
  <boundary>0 1
   0 2
   0 3
   0 4
  </boundary>
 </MultiPatch>
</xml>

